fromager/__main__.py
fromager/bootstrapper.py
fromager/build_environment.py
fromager/candidate.py
fromager/clickext.py
fromager/constraints.py
fromager/context.py
fromager/dependencies.py
fromager/dependency_graph.py
fromager/external_commands.py
fromager/extras_provider.py
fromager/finders.py
fromager/gitutils.py
fromager/hooks.py
fromager/http_retry.py
fromager/log.py
fromager/metrics.py
fromager/overrides.py
fromager/packagesettings.py
fromager/progress.py
fromager/py.typed
fromager/pyproject.py
fromager/read.py
fromager/request_session.py
fromager/requirements_file.py
fromager/resolver.py
fromager/run_network_isolation.sh
fromager/server.py
fromager/sources.py
fromager/tarballs.py
fromager/threading_utils.py
fromager/vendor_rust.py
fromager/versionmap.py
fromager/wheels.py
fromager/commands/__init__.py
fromager/commands/bootstrap.py
fromager/commands/build.py
fromager/commands/build_order.py
fromager/commands/canonicalize.py
fromager/commands/download_sequence.py
fromager/commands/find_updates.py
fromager/commands/graph.py
fromager/commands/lint.py
fromager/commands/lint_requirements.py
fromager/commands/list_overrides.py
fromager/commands/list_versions.py
fromager/commands/migrate_config.py
fromager/commands/minimize.py
fromager/commands/server.py
fromager/commands/stats.py
fromager/commands/step.py
fromager/pkgmetadata/__init__.py
fromager/pkgmetadata/pep639.py
fromager/pkgmetadata/pep753.py
fromager-0.75.0.dist-info/METADATA
fromager-0.75.0.dist-info/WHEEL
fromager-0.75.0.dist-info/entry_points.txt
fromager-0.75.0.dist-info/licenses/LICENSE
fromager-0.75.0.dist-info/RECORD
