Metadata-Version: 2.4
Name: fromager
Version: 0.75.0
Summary: Wheel maker
Project-URL: Repository, https://github.com/python-wheel-build/fromager
Project-URL: Documentation, https://fromager.readthedocs.io/en/latest/
Author-email: Mark McLoughlin <markmc@redhat.com>, Doug Hellmann <dhellmann@redhat.com>
License: 
License-File: LICENSE
Classifier: Development Status :: 5 - Production/Stable
Classifier: Environment :: Console
Classifier: Intended Audience :: Developers
Classifier: License :: OSI Approved :: Apache Software License
Classifier: Operating System :: OS Independent
Classifier: Programming Language :: Python
Classifier: Programming Language :: Python :: 3
Classifier: Programming Language :: Python :: 3 :: Only
Classifier: Programming Language :: Python :: 3.11
Classifier: Programming Language :: Python :: 3.12
Classifier: Programming Language :: Python :: 3.13
Classifier: Programming Language :: Python :: Implementation :: CPython
Classifier: Topic :: Utilities
Requires-Python: >=3.11
Requires-Dist: click>=8.1.7
Requires-Dist: elfdeps>=0.2.0
Requires-Dist: license-expression
Requires-Dist: packaging
Requires-Dist: pkginfo
Requires-Dist: psutil
Requires-Dist: pydantic
Requires-Dist: pypi-simple
Requires-Dist: pyproject-hooks!=1.1.0,>=1.0.0
Requires-Dist: pyyaml
Requires-Dist: requests
Requires-Dist: requests-mock
Requires-Dist: resolvelib
Requires-Dist: rich
Requires-Dist: starlette
Requires-Dist: stevedore
Requires-Dist: tomlkit
Requires-Dist: tqdm
Requires-Dist: uv>=0.8.19
Requires-Dist: uvicorn
Requires-Dist: wheel
Provides-Extra: build
Requires-Dist: build; extra == 'build'
Requires-Dist: twine; extra == 'build'
Provides-Extra: docs
Requires-Dist: autodoc-pydantic; extra == 'docs'
Requires-Dist: myst-parser; extra == 'docs'
Requires-Dist: sphinx; extra == 'docs'
Requires-Dist: sphinx-click; extra == 'docs'
Requires-Dist: sphinx-rtd-theme; extra == 'docs'
Provides-Extra: mypy
Requires-Dist: mypy; extra == 'mypy'
Requires-Dist: pytest; extra == 'mypy'
Requires-Dist: types-html5lib; extra == 'mypy'
Requires-Dist: types-psutil; extra == 'mypy'
Requires-Dist: types-pyyaml; extra == 'mypy'
Requires-Dist: types-requests; extra == 'mypy'
Requires-Dist: types-toml; extra == 'mypy'
Requires-Dist: types-tqdm; extra == 'mypy'
Provides-Extra: test
Requires-Dist: click!=8.3.0; extra == 'test'
Requires-Dist: coverage[toml]!=4.4,>=4.0; extra == 'test'
Requires-Dist: hatch-vcs; extra == 'test'
Requires-Dist: hatchling; extra == 'test'
Requires-Dist: pytest; extra == 'test'
Requires-Dist: requests-mock; extra == 'test'
Requires-Dist: twine>=6.1.0; extra == 'test'
